{
  "slug": "Aires_Mateus_Associados",
  "architekt": {
    "name": "Aires Mateus Associados",
    "nachname": "Aires",
    "vorname": "Mateus Associados",
    "jahre": [],
    "ordner": "Aires_Mateus_Associados"
  },
  "pfad": "/Volumes/daten/05_Architekten_Synobsis/Aires_Mateus_Associados",
  "projekte": [
    {
      "raw": "Casa_No_Litoeal_Alentejano",
      "ort": "Casa",
      "projekt": "No Litoeal Alentejano",
      "jahre": [],
      "titel": "Casa No Litoeal Alentejano"
    },
    {
      "raw": "Casa_em_Alenquer",
      "ort": "Casa",
      "projekt": "em Alenquer",
      "jahre": [],
      "titel": "Casa em Alenquer"
    },
    {
      "raw": "CentroEscolar_Barquina",
      "ort": "CentroEscolar",
      "projekt": "Barquina",
      "jahre": [],
      "titel": "CentroEscolar Barquina"
    },
    {
      "raw": "St_Gallen",
      "ort": "St",
      "projekt": "Gallen",
      "jahre": [],
      "titel": "St Gallen"
    },
    {
      "raw": "aires_mateus",
      "ort": "aires",
      "projekt": "mateus",
      "jahre": [],
      "titel": "aires mateus"
    }
  ],
  "projekt_anzahl": 5,
  "inventar": {
    "bilder": 12,
    "dokumente": 7,
    "cad": 0,
    "andere": 1,
    "total": 20
  },
  "dateitypen": {
    ".jpg": 10,
    ".pdf": 7,
    ".gif": 2,
    ".indd": 1
  },
  "textauszug": "80 Patiohaus eingeschossig Nord-Süd-Orientierung Das eingeschossige Hofhaus wird durch vier Patios perforiert. Ähnlich wie bei dem nachfolgenden Beispiel von Ryue Nishizawa entsteht ein räumliches Panoptikum, welches zur Auflösung der klassischen Kategorien von Indivi- dual- und Gemeinschaftsräumen führt. Entlang der Außenwände gruppieren sich insgesamt drei Raumbereiche, die als Individualraum nutzbar wären. Zwei von diesen drei Räumen verfügen über eigene Sanitärräume. Die Gemein- schaftszonen befinden sich im Zentrum des Hauses um einen etwas größeren Innenhof herum gruppiert. Das Haus ist an zwei Seiten anbaufähig und bietet darüber hinaus zwei potenzielle Erschließungsseiten. Der Typ eignet sich dadurch als Siedlungsbaustein. Die starke Introversion bedarf bei der Verwendung dieses Typs auf dem mitteleuropäischen Breitengrad einiger Veränderungen und Überarbeitungen. Querschnitt Dachaufsicht Erdgeschoss Einzelhaus „Casa No Litoral Alentejano“ Grandola, 2000 Aires Mateus & Associados 81",
  "embed_doc": "Aires Mateus Associados | Casa No Litoeal Alentejano | Casa em Alenquer | CentroEscolar Barquina | St Gallen | aires mateus | 80 Patiohaus eingeschossig Nord-Süd-Orientierung Das eingeschossige Hofhaus wird durch vier Patios perforiert. Ähnlich wie bei dem nachfolgenden Beispiel von Ryue Nishizawa entsteht ein räumliches Panoptikum, welches zur Auflösung der klassischen Kategorien von Indivi- dual- und Gemeinschaftsräumen führt. Entlang der Außenwände gruppieren sich insgesamt drei Raumbereiche, die als Individualraum nutzbar wären. Zwei von diesen drei Räumen verfügen über eigene Sanitärräume. Die Gemein- schaftszonen befinden sich im Zentrum des Hauses um einen etwas größeren Innenhof herum gruppiert. Das Haus ist an zwei Seiten anbaufähig und bietet darüber hinaus zwei potenzielle Erschließungsseiten. Der Typ eignet sich dadurch als Siedlungsbaustein. Die starke Introversion bedarf bei der Verwendung dieses Typs auf dem mitteleuropäischen Breitengrad einiger Veränderungen und Überarbeitungen. Querschnitt Dachaufsicht Erdgeschoss Einzelhaus „Casa No Litoral Alentejano“ Grandola, 2000 Aires Mateus & Associados 81",
  "stand": "2026-07-02T21:05:31"
}