{
  "slug": "Geissbuehler_Dietere",
  "architekt": {
    "name": "Geissbuehler Dietere",
    "nachname": "Geissbuehler",
    "vorname": "Dietere",
    "jahre": [],
    "ordner": "Geissbuehler_Dietere"
  },
  "pfad": "/Volumes/daten/05_Architekten_Synobsis/Geissbuehler_Dietere",
  "projekte": [
    {
      "raw": "00_Architekten",
      "ort": "00",
      "projekt": "Architekten",
      "jahre": [],
      "titel": "00 Architekten"
    }
  ],
  "projekt_anzahl": 1,
  "inventar": {
    "bilder": 1,
    "dokumente": 6,
    "cad": 0,
    "andere": 0,
    "total": 7
  },
  "dateitypen": {
    ".pdf": 5,
    ".docx": 1,
    ".jpg": 1
  },
  "textauszug": "Buch der Woche VOM MATERIAL ZUR FORM Text: Palle Petersen / 19.09.2012 00:00 Wenig Positives passiere derzeit in der Welt des Bauens, meint Dieter Geissbühler und kritisiert: Digitalisierung distanziere vom realen Gegenstand , energetische Optimierung führe zu gestalterischer Gleichförmigkeit und die Kapitalisierung nivelliere die Bauproduktion. Vor allem aber entferne sich der Architekt vom Generalistentum und von der Konstruktion. Hier setzt die Geissbühlersche Rosskur für den Entwurfsprozess an: Die drängenden Fragen einer nachhaltigen Bauproduktion können für den Buchautor nur durch profunde Materialkenntnis und kritische Forschung beantwortet werden. Geissbühler argumentiert gegen vielschichtige Fassaden, aber gleichzeitig für differenzierte Konstruktionsprinzipien, gegen die Abstraktion und für die Physis. Gleichzeitig allerdings auch für die Metaphysis und die kulturelle Dimension der Architektur. In diesem Spannungsfeld fehlt leider der Fokus, und die wenigen Kernaussagen werden gebetsmühlenartig wiederholt. Zahlreiche interessante Zitate und gebaute Beispiele machen diesen dritten Band der laboratorium -Reihe vom Departement Technik & Architektur der Hochschule Luzern dennoch lesenswert. 11.02.13 14:57Das Klima als Entwurfsfaktor Seite 1 von 1http://www.quart.ch/laboratorium-de.php?nID=315 Bilder: 1 112 Seiten, 17 x 22 cm27 Abbildungen, 119 PläneFadengeheftete BroschurCHF 34.–/EUR 24.– Deutsch; teilweise Englisch ISBN 978-3-03761-010-7 HomeNovitätenGesamtverzeichnisSubskriptionWarenkorbSuchenDE | EN De aedibusDe aedibus internationalAnthologieMonografienArchitekturführerArcadiaBibliothecaPanta rheiNotatioEinzelausgabenLaboratorium › __ NewsNewsletterVerlagsprogrammPressespiegelVerlagsportraitPresseKontakt Das Klima als Entwurfsfaktor In diesem Band wird das Klima als Entwurfsfaktor untersucht und seinEinfluss auf energetische und gestalterische Konsequenzen überprüft.Die Blickweise ist nicht eine abstrakt-technische, sondern eineanschaulich-räumliche, welche die Suche nach inspirierenden Lösungenbewusst stimuliert. zurück zur Übersicht › Quart Verlag GmbH | Heinz Wirz | Verlag für Architektur und Kunst | Tel. +41 (0)41 420 20 82 | books@quart.ch | Impressum | AGBs | 11.02.13 14:57Forschende Architektur Seite 1 von 1http://www.quart.ch/laboratorium-de.php?nID=356 Bilder: 1 2 3 104 Seiten, 17 x 22 cm50 Abbildungen, 13 Diagramme und PläneFadengeheftete BroschurCHF 34.–/EUR 24.– kaufen Deutsch ISBN 978-3-03761-019-0 kaufen Englisch ISBN 978-3-03761-023-7 HomeNovitätenGesamtverzeichnisSubskriptionWarenkorbSuchenDE | EN De aedibusDe aedibus internationalAnthologieMonografienArchitekturführerArcadiaBibliothecaPanta rheiNotatioEinzelausgabenLaboratorium › __ NewsNewsletterVerlagsprogrammPressespiegelVerlagsportraitPresseKontakt Forschende Architektur Mit dem zweiten Band der Reihe Laboratorium wird eine Position in derweiträumigen Diskussion über Forschung und dem architek-tonischenSchaffensprozess bezogen. Fallbeispiele zeigen auf, wie individuellWissen in den Entwurf einfliessen und so kommunizierbar gemachtwerden kann. Text: Andri Gerber, Tina Unruh, Dieter Geissbühler zurück zur Übersicht › Quart Verlag GmbH | Heinz Wirz | Verlag für Architektur und Kunst | Tel. +41 (0)41 420 20 82 | books@quart.ch | Impressum | AGBs | 11.02.13 14:58Räumliches Denken Seite 1 von 1http://www.quart.ch/laboratorium-de.php?nID=446 Bilder: 1 2 84 Seiten, 17 x 22 cmCa. 50 Abbildungen, Pläne und DiagrammeFadengeheftete BroschurCHF 34.–/EUR 24.– kaufen Deutsch ISBN 978-3-03761-041-1 kaufen Englisch ISBN 978-3-03761-055-8 HomeNovitätenGesamtverzeichnisSubskriptionWarenkorbSuchenDE | EN De aedibusDe aedibus internationalAnthologieMonografienArchitekturführerArcadiaBibliothecaPanta rheiNotatioEinzelausgabenLaboratorium › __ NewsNewsletterVerlagsprogrammPressespiegelVerlagsportraitPresseKontakt Räumliches Denken Im Zentrum dieses Bandes steht die Frage nach der entwerferischenRelevanz von Werkstoffen in der Geschichte und der Gegenwart. Indiesem Rahmen steht auch die Analyse, wie alternativeKonstruktionsprinzipien «erforscht» werden können und womassgebende Entwicklungsimpulse angelegt sind. Herausgeber: Hochschule Luzern – Technik & Architektur; CC Material,Struktur und Energie in Architektur, Tina Unruh Autor: Dieter GeissbühlerVorwort: Tina Unruh zurück zur Übersicht › Quart Verlag GmbH | Heinz Wirz | Verlag für Architektur und Kunst | Tel. +41 (0)41 420 20 82 | books@quart.ch | Impressum | AGBs | Forschende Architektur Andri Gerber, Tina Unruh, Dieter Geissbühler Quart Verlag Luzern Vorwort 7 Versuchsanordnung 9 Artenvielfalt 13 Feldstudien 28 Glossar 29 Jean Prouve 36 Aldo Rossi 44 Peter Eisenman 54 Christopher Alexander 62 Peter Zumthor 70 Notizen 76 Resultat 80 Von Keksen und Einfamilienhäusern 83 Anhang 98",
  "embed_doc": "Geissbuehler Dietere | 00 Architekten | Buch der Woche VOM MATERIAL ZUR FORM Text: Palle Petersen / 19.09.2012 00:00 Wenig Positives passiere derzeit in der Welt des Bauens, meint Dieter Geissbühler und kritisiert: Digitalisierung distanziere vom realen Gegenstand , energetische Optimierung führe zu gestalterischer Gleichförmigkeit und die Kapitalisierung nivelliere die Bauproduktion. Vor allem aber entferne sich der Architekt vom Generalistentum und von der Konstruktion. Hier setzt die Geissbühlersche Rosskur für den Entwurfsprozess an: Die drängenden Fragen einer nachhaltigen Bauproduktion können für den Buchautor nur durch profunde Materialkenntnis und kritische Forschung beantwortet werden. Geissbühler argumentiert gegen vielschichtige Fassaden, aber gleichzeitig für differenzierte Konstruktionsprinzipien, gegen die Abstraktion und für die Physis. Gleichzeitig allerdings auch für die Metaphysis und die kulturelle Dimension der Architektur. In diesem Spannungsfeld fehlt leider der Fokus, und die wenigen Kernaussagen werden gebetsmühlenartig wiederholt. Zahlreiche interessante Zitate und gebaute Beispiele machen diesen dritten Band der laboratorium -Reihe vom Departement Technik & Architektur der Hochschule Luzern dennoch lesenswert. 11.02.13 14:57Das Klima als Entwurfsfaktor Seite 1 von 1http://www.quart.ch/laboratorium-de.php?nID=315 Bilder: 1 112 Seiten, 17 x 22 cm27 Abbildungen, 119 PläneFadengeheftete BroschurCHF 34.–/EUR 24.– Deutsch; teilweise Englisch ISBN 978-3-03761-010-7 HomeNovitätenGesamtverzeichnisSubskriptionWarenkorbSuchenDE | EN De aedibusDe aedibus internationalAnthologieMonografienArchitekturführerArcadiaBibliothecaPanta rheiNotatioEinzelausgabenLaboratorium › __ NewsNewsletterVerlagsprogrammPressespiegelVerlagsportraitPresseKontakt Das Klima als Entwurfsfaktor In diesem Band wird das Klima als Entwurfsfaktor untersucht und seinEinfluss auf energetische und gestalterische Konsequenzen überprüft.Die Blickweise ist nicht eine abstrakt-technische, sondern eineanschaulich-räumliche, welche die Suche nach inspirierenden Lösungenbewusst stimuliert. zurück zur Übersicht › Quart Verlag GmbH | Heinz Wirz | Verlag für Architektur und Kunst | Tel. +41 (0)41 420 20 82 | books@quart.ch | Impressum | AGBs | 11.02.13 14:57Forschende Architektur Seite 1 von 1http://www.quart.ch/laboratorium-de.php?nID=356 Bilder: 1 2 3 104 Seiten, 17 x 22 cm50 Abbildungen, 13 Diagramme und PläneFadengeheftete BroschurCHF 34.–/EUR 24.– kaufen Deutsch ISBN 978-3-03761-019-0 kaufen Englisch ISBN 978-3-03761-023-7 HomeNovitätenGesamtverzeichnisSubskriptionWarenkorbSuchenDE | EN De aedibusDe aedibus internationalAnthologieMonografienArchitekturführerArcadiaBibliothecaPanta rheiNotatioEinzelausgabenLaboratorium › __ NewsNewsletterVerlagsprogrammPressespiegelVerlagsportraitPresseKontakt Forschende Architektur Mit dem zweiten Band der Reihe Laboratorium wird eine Position in derweiträumigen Diskussion über Forschung und dem architek-tonischenSchaffensprozess bezogen. Fallbeispiele zeigen auf, wie individuellWissen in den Entwurf einfliessen und so kommunizierbar gemachtwerden kann. Text: Andri Gerber, Tina Unruh, Dieter Geissbühler zurück zur Übersicht › Quart Verlag GmbH | Heinz Wirz | Verlag für Architektur und Kunst | Tel. +41 (0)41 420 20 82 | books@quart.ch | Impressum | AGBs | 11.02.13 14:58Räumliches Denken Seite 1 von 1http://www.quart.ch/laboratorium-de.php?nID=446 Bilder: 1 2 84 Seiten, 17 x 22 cmCa. 50 Abbildungen, Pläne und DiagrammeFadengeheftete BroschurCHF 34.–/EUR 24.– kaufen Deutsch ISBN 978-3-03761-041-1 kaufen Englisch ISBN 978-3-03761-055-8 HomeNovitätenGesamtverzeichnisSubskriptionWarenkorbSuchenDE | EN De aedibusDe aedibus internationalAnthologieMonografienArchitekturführerArcadiaBibliothecaPanta rheiNotatioEinzelausgabenLaboratorium › __ NewsNewsletterVerlagsprogrammPressespiegelVerlagsportraitPresseKontakt Räumliches Denken Im Zentrum dieses Bandes steht die Frage nach der entwerferischenRelevanz von Werkstoffen in der Geschichte und der Gegenwart. Indiesem Rahmen steht auch die Analyse, wie alternativeKonstruktionsprinzipien «erforscht» werden können und womassgebende Entwicklungsimpulse angelegt sind. Herausgeber: Hochschule Luzern – Technik & Architektur; CC Material,Struktur und Energie in Architektur, Tina Unruh Autor: Dieter GeissbühlerVorwort: Tina Unruh zurück zur Übersicht › Quart Verlag GmbH | Heinz Wirz | Verlag für Architektur und Kunst | Tel. +41 (0)41 420 20 82 | books@quart.ch | Impressum | AGBs | Forschende Architektur Andri Gerber, Tina Unruh, Dieter Geissbühler Quart Verlag Luzern Vorwort 7 Versuchsanordnung 9 Artenvielfalt 13 Feldstudien 28 Glossar 29 Jean Prouve 36 Aldo Rossi 44 Peter Eisenman 54 Christopher Alexander 62 Peter Zumthor 70 Notizen 76 Resultat 80 Von Keksen und Einfamilienhäusern 83 Anhang 98",
  "stand": "2026-07-02T21:16:02"
}