{
  "slug": "Leutwiler_Architekten",
  "architekt": {
    "name": "Leutwiler Architekten",
    "nachname": "Leutwiler",
    "vorname": "Architekten",
    "jahre": [],
    "ordner": "Leutwiler_Architekten"
  },
  "pfad": "/Volumes/daten/05_Architekten_Synobsis/Leutwiler_Architekten",
  "projekte": [],
  "projekt_anzahl": 0,
  "inventar": {
    "bilder": 0,
    "dokumente": 1,
    "cad": 0,
    "andere": 0,
    "total": 1
  },
  "dateitypen": {
    ".pdf": 1
  },
  "textauszug": "07.12.12 11:28leutwyler architekten Seite 1 von 2http://www.leutwylerarchitekten.ch/projekte/patio leutwyler architekten Patio Zug Eine Wohnung in einem Mehrfamilienhaus wurde zur Oase für den Bauherrn: Ein Pa- tio inmitten der Wohnung, mit Bambusgarten und einem kleinen Schlafraum, bietet Ruhe und Geborgenheit inmitten der Stadt. Die Umfassungsmauern des Patios beste- hen aus Kalkstein, seine Einbauten aus Eichenholz. Die warmen Materialien und die Grün- und Weisstöne des Gartens schaffen eine meditative Stimmung in diesem fast schalldichten Raum. Der Patio und die angrenzenden Wohnräume sind durch raumho- he Verglasungen getrennt. Bei Bedarf kann der Patio aber auch komplett isoliert wer- den, indem die Holzläden an den Fenstern verschlossen werden. Im Garten ist Wasser ein wichtiges Gestaltungselement. Ein Brunnen – wahlweise mit hörbarem oder leisem Zulauf – verstärkt die idyllische Atmosphäre. An den Patio schliesst ein Ruheraum an, der stimmungsvoll beleuchtet ist. In einer mit Eichenholz ausgekleideten Nische ist ein Bett integriert. Aufgrund der gleichen Materi- alwahl werden Ruheraum und Patio als Einheit wahrgenommen. 07.12.12 11:28leutwyler architekten Seite 2 von 2http://www.leutwylerarchitekten.ch/projekte/patio Bauherrschaft: Privat Fertigstellung: 2008 Auftragsart: Direktauftrag",
  "embed_doc": "Leutwiler Architekten | 07.12.12 11:28leutwyler architekten Seite 1 von 2http://www.leutwylerarchitekten.ch/projekte/patio leutwyler architekten Patio Zug Eine Wohnung in einem Mehrfamilienhaus wurde zur Oase für den Bauherrn: Ein Pa- tio inmitten der Wohnung, mit Bambusgarten und einem kleinen Schlafraum, bietet Ruhe und Geborgenheit inmitten der Stadt. Die Umfassungsmauern des Patios beste- hen aus Kalkstein, seine Einbauten aus Eichenholz. Die warmen Materialien und die Grün- und Weisstöne des Gartens schaffen eine meditative Stimmung in diesem fast schalldichten Raum. Der Patio und die angrenzenden Wohnräume sind durch raumho- he Verglasungen getrennt. Bei Bedarf kann der Patio aber auch komplett isoliert wer- den, indem die Holzläden an den Fenstern verschlossen werden. Im Garten ist Wasser ein wichtiges Gestaltungselement. Ein Brunnen – wahlweise mit hörbarem oder leisem Zulauf – verstärkt die idyllische Atmosphäre. An den Patio schliesst ein Ruheraum an, der stimmungsvoll beleuchtet ist. In einer mit Eichenholz ausgekleideten Nische ist ein Bett integriert. Aufgrund der gleichen Materi- alwahl werden Ruheraum und Patio als Einheit wahrgenommen. 07.12.12 11:28leutwyler architekten Seite 2 von 2http://www.leutwylerarchitekten.ch/projekte/patio Bauherrschaft: Privat Fertigstellung: 2008 Auftragsart: Direktauftrag",
  "stand": "2026-07-02T21:42:40"
}