{
  "slug": "Moretti_Luigi",
  "architekt": {
    "name": "Moretti Luigi",
    "nachname": "Moretti",
    "vorname": "Luigi",
    "jahre": [],
    "ordner": "Moretti_Luigi"
  },
  "pfad": "/Volumes/daten/05_Architekten_Synobsis/Moretti_Luigi",
  "projekte": [
    {
      "raw": "00_Erdgeschoss",
      "ort": "00",
      "projekt": "Erdgeschoss",
      "jahre": [],
      "titel": "00 Erdgeschoss"
    },
    {
      "raw": "00_unklar",
      "ort": "00",
      "projekt": "unklar",
      "jahre": [],
      "titel": "00 unklar"
    },
    {
      "raw": "Casa_della_Gioventu_Italiana_del_Littorio",
      "ort": "Casa",
      "projekt": "della Gioventu Italiana del Littorio",
      "jahre": [],
      "titel": "Casa della Gioventu Italiana del Littorio"
    },
    {
      "raw": "Einfamilienhaus",
      "ort": "Einfamilienhaus",
      "projekt": "Einfamilienhaus",
      "jahre": [],
      "titel": "Einfamilienhaus"
    },
    {
      "raw": "La_Saracena",
      "ort": "La",
      "projekt": "Saracena",
      "jahre": [],
      "titel": "La Saracena"
    },
    {
      "raw": "Mailand_Buerobau_Corso_Italia",
      "ort": "Mailand",
      "projekt": "Buerobau Corso Italia",
      "jahre": [],
      "titel": "Mailand Buerobau Corso Italia"
    },
    {
      "raw": "Rom_Fechtakademie_Foro_Italico",
      "ort": "Rom",
      "projekt": "Fechtakademie Foro Italico",
      "jahre": [],
      "titel": "Rom Fechtakademie Foro Italico"
    },
    {
      "raw": "Rom_Palazzina_Girasole_1948_50",
      "ort": "Rom",
      "projekt": "Palazzina Girasole 50",
      "jahre": [
        "1948"
      ],
      "titel": "Rom Palazzina Girasole 1948 50"
    },
    {
      "raw": "Rom_Palazzina_Maurizio_1962",
      "ort": "Rom",
      "projekt": "Palazzina Maurizio",
      "jahre": [
        "1962"
      ],
      "titel": "Rom Palazzina Maurizio 1962"
    },
    {
      "raw": "Rom_Villa_Borghese_Roma_1965_1972",
      "ort": "Rom",
      "projekt": "Villa Borghese Roma",
      "jahre": [
        "1965",
        "1972"
      ],
      "titel": "Rom Villa Borghese Roma 1965 1972"
    },
    {
      "raw": "Wohnhaus",
      "ort": "Wohnhaus",
      "projekt": "Wohnhaus",
      "jahre": [],
      "titel": "Wohnhaus"
    }
  ],
  "projekt_anzahl": 11,
  "inventar": {
    "bilder": 174,
    "dokumente": 13,
    "cad": 0,
    "andere": 0,
    "total": 187
  },
  "dateitypen": {
    ".jpg": 169,
    ".pdf": 10,
    ".tif": 4,
    ".docx": 3,
    ".jpeg": 1
  },
  "textauszug": "17.06.12 13:10Opportunistischer Alleskönner - Neue Zürcher Zeitung Seite 1 von 4http://mobile.nzz.ch/kultur/kunst_architektur/opportunistischer_alleskoenner_1.15553525.html Donnerstag, 8. März, 06:00 STARTSEITE Der italienische Architekt Luigi Moretti (1907–1973) in der Architekturakademie Mendrisio Opportunistischer Alleskönner Im Kreis der faschistischen Architekten Roms galt Luigi Moretti als Vermittler zwischen totalitärer Monumentalität und rationalistischer Moderne. Nach dem Krieg fand er im Dialog mit Borrominis Barock und der ungegenständlichen Kunst zu neuen Ausdrucksformen. Von Roman Hollenstein Makellose Pläne und perfekte Renderings gehören heute zum architektonischen Alltag. So verführerisch sie sein mögen, fehlt ihnen doch jene Aura des Schöpferischen, welche etwa die Skizzen und Zeichnungen des Römer Architekten Luigi Moretti (1907–1973) verströmen. Sie standen am Anfang von Meisterwerken wie dem grandiosen Wohn- und Geschäftshaus am Corso Italia in Mailand, vor dem wohl schon manch ein Tourist verblüfft innegehalten hat. Scheint doch der Bug des Scheibenhochhauses wie ein Ozeanriese aus dem abstrakten Wellental des Sockelbaus in den Strassenraum vorzustossen. Man könnte in dieser 1956 vollendeten Perle der italienischen Nachkriegsarchitektur den Geniestreich eines jungen Navigation 17.06.12 13:10Opportunistischer Alleskönner - Neue Zürcher Zeitung Seite 2 von 4http://mobile.nzz.ch/kultur/kunst_architektur/opportunistischer_alleskoenner_1.15553525.html vollendeten Perle der italienischen Nachkriegsarchitektur den Geniestreich eines jungen Wilden vermuten, der den Ballast der Schule abgeworfen und sich auf ein waghalsiges Konstruktionsmanöver eingelassen hat. Doch der damals 49-jährige Moretti wollte sich mit diesem spektakulären Befreiungsschlag von einer ganz anderen Last lösen: seiner monumentalen, mit raffinierter Rhetorik die Macht des Duce verherrlichenden Raumkunst, die vor dem Zweiten Weltkrieg in Bauten, Platzanlagen und Wettbewerbsentwürfen immer neue Triumphe feierte. Monumentale Visionen Am Anfang der umfassenden Werkschau, die derzeit in der Galerie der Architekturakademie Mendrisio zu sehen ist, stehen prachtvolle farbige Präsentationszeichnungen aus den späten 1930er Jahren, als Moretti sich mit Leidenschaft an die Verfeinerung der faschistischen Ikonographie machte. Mit den detailreichen Bildtafeln, die neben der Architektur, dem Raum und dem Licht auch die Ausgestaltung der Aussen- und Innenräume bis hin zu den Mosaiken und Skulpturengruppen wiedergeben, versuchte Moretti die nationalen Wettbewerbe des Palazzo del Littorio und des Piazzale del Impero für sich zu entscheiden. Auf der Empore des Ausstellungssaals sieht man sich mit ihrer martialischen Ausstrahlung konfrontiert. Anschliessend kann man unten im langgestreckten Galerieraum und im separaten Modellsaal die Zeugnisse des vielschichtigen Entwurfsprozesses entschlüsseln. Sie geben einen Eindruck von der Kreativität Morettis, der sich wie viele andere Künstler seiner Zeit – nicht nur in Italien – von den ihm durch die Diktatur gebotenen Möglichkeiten hatte blenden lassen. Doch anders als der geniale Giuseppe Terragni, der an seinem Irrtum zugrunde ging, verstand es der Konformist Moretti, sich nach dem Krieg mit Leichtigkeit neu zu erfinden. Bereits als Student realisierte der im architektonischen Ambiente Roms aufgewachsene Moretti seine ersten Häuser – etwa 1931 eine schöne, vom klassizistischen Mailänder Novecento und vom Vokabular des späteren Staatsarchitekten Marcello Piacentini beeinflusste Stadtvilla in Ostia. Dann entdeckte er die rationalistische Moderne und schuf zwischen 1933 und 1936 mehrere der faschistischen Jugend gewidmete Case Balilla, darunter jene von Trastevere. Während das Zusammenspiel der modernistischen Volumen und des etwas plumpen, mit dem obligaten Balkon versehenen Turms irritiert, vermögen die eleganten Innenräume zu punkten. Solch rationalistischen Fingerübungen folgte die sich durch eine meisterhaft inszenierte Plastizität auszeichnende, später zur Accademia della Scherma umfunktionierte Casa Balilla sperimentale am Foro Mussolini (dem späteren Foro Italico), wo Moretti neben dem Piazzale del Impero auch die geschmäcklerische Palestra del Duce realisierte: einen Marmortempel, in dessen minimalistischen Säulenhallen sich Mussolini ertüchtigen konnte. Damals schon übte sich Moretti in unterschiedlichen Formensprachen und entwarf ganz im Geist der Pittura Metafisica eine rätselhaft anmutende Villa am Meer. Nach dem Krieg kam er für seine faschistische Kollaboration kurz ins Gefängnis. Danach verliess er Rom, um in Mailand den Neuanfang zu wagen. Die ersten Bauten, die mit seiner Firma Cofimprese in der lombardischen Metropole realisierten «Case-Albergo», waren noch dem Rationalismus verpflichtet, veranschaulichten aber mit Lochfenstern oder sich geradezu dekonstruktivistisch von der Tragstruktur ablösenden Fassaden bereits Morettis architektonischen Dialog mit der ungegenständlichen Kunst (etwa eines Lucio Fontana). Zurück in Rom, sagt er sich 1949 mit dem Astrea-Wohnblock, dessen Fassaden schuppenartig abstehen, vom doktrinären Rationalismus los; und mit der mittig gespaltenen Palazzina Girasole (1950), die sich über einem ruppigen Steinsockel erhebt, gelingt ihm sein erster 17.06.12 13:10Opportunistischer Alleskönner - Neue Zürcher Zeitung Seite 3 von 4http://mobile.nzz.ch/kultur/kunst_architektur/opportunistischer_alleskoenner_1.15553525.html ImpressumAGBCopyrightWerbungWechsel zur Webansicht Girasole (1950), die sich über einem ruppigen Steinsockel erhebt, gelingt ihm sein erster Capolavoro der Nachkriegszeit, der zur Inspiration für Robert Venturi, den Papst der Postmoderne, werden sollte. Form und Raum Im selben Jahr gründet er die Zeitschrift «Spazio», in der er die informelle Kunst für die Architektur zu nutzen sucht und neue Anregung bei Borrominis Barock und Michelangelos Manierismus findet. Die von seinem Widersacher, dem eine ethische Architektur fordernden Bruno Zevi, propagierte organische Baukunst stösst auch bei Moretti auf Interesse. Er weiss sie in sein logisch-mathematisches Theoriegebäude zu integrieren, wie ein weiteres Highlight beweist: die auf Kreisen und Ovalen basierende Villa «La Saracena» in Santa Marinella (1957), zu der Annalisa Viati Navone, die zusammen mit Bruno Reichlin die Ausstellung betreute, soeben eine ausführliche Studie veröffentlicht hat. Organische Gestaltungsprinzipien prägen später auch die Watergate-Residenz in Washington (1965), die Thermen von Fiuggi (1969) sowie drei zwischen 1964 und 1972 konzipierte Römer Projekte: den San-Maurizio-Wohnblock, die seltsame, an ein brütendes Huhn erinnernde Chiesa Santa Maria Ecclesiae und die skulpturale Tiefgarage unter dem Park der Villa Borghese. Anders als Zevi verstand Moretti die organische Baukunst nicht als politische Aussage, sondern als rein formale Geste, wie sein im Auftrag des Vatikans projektiertes, aber unrealisiert gebliebenes Sanktuarium am See Genezareth demonstriert. Hier versuchte er Frank Lloyd Wright zu übertreffen. Er mass sich jedoch auch mit anderen Grössen seiner Zeit. So antwortet die zusammen mit dem Meisteringenieur Pier Luigi Nervi geplante Tour de la Bourse in Montreal auf Mies van der Rohes Seagram Building in New York und auf das Pirelli-Hochhaus von Gio Ponti und Nervi in Mailand. Auf all diese Werke geht der opulente Katalog, der leider weder über eine (an sich leicht erstellbare) Liste der realisierten Gebäude noch über ein Werkverzeichnis verfügt, ausführlich ein. Aber selbst die faschistischen Bauten werden in erster Linie in Bezug auf Form und Raum analysiert. Damit wird dem erfindungsreichen Architekten ein verdientes Denkmal errichtet, aber einmal mehr auf eine über Andeutungen hinausgehende kritisch-zeitgeschichtliche Auseinandersetzung mit dem opportunistischen Alleskönner verzichtet. Bis 8. April (Di–Fr von 16–19.30 Uhr, Sa u. So von 13–18 Uhr). Katalog: Luigi Moretti. Razionalismo e trasgressività tra baroc",
  "embed_doc": "Moretti Luigi | 00 Erdgeschoss | 00 unklar | Casa della Gioventu Italiana del Littorio | Einfamilienhaus Einfamilienhaus | La Saracena | Mailand Buerobau Corso Italia | Rom Fechtakademie Foro Italico | Rom Palazzina Girasole 50 1948 | Rom Palazzina Maurizio 1962 | Rom Villa Borghese Roma 1965 1972 | Wohnhaus Wohnhaus | 17.06.12 13:10Opportunistischer Alleskönner - Neue Zürcher Zeitung Seite 1 von 4http://mobile.nzz.ch/kultur/kunst_architektur/opportunistischer_alleskoenner_1.15553525.html Donnerstag, 8. März, 06:00 STARTSEITE Der italienische Architekt Luigi Moretti (1907–1973) in der Architekturakademie Mendrisio Opportunistischer Alleskönner Im Kreis der faschistischen Architekten Roms galt Luigi Moretti als Vermittler zwischen totalitärer Monumentalität und rationalistischer Moderne. Nach dem Krieg fand er im Dialog mit Borrominis Barock und der ungegenständlichen Kunst zu neuen Ausdrucksformen. Von Roman Hollenstein Makellose Pläne und perfekte Renderings gehören heute zum architektonischen Alltag. So verführerisch sie sein mögen, fehlt ihnen doch jene Aura des Schöpferischen, welche etwa die Skizzen und Zeichnungen des Römer Architekten Luigi Moretti (1907–1973) verströmen. Sie standen am Anfang von Meisterwerken wie dem grandiosen Wohn- und Geschäftshaus am Corso Italia in Mailand, vor dem wohl schon manch ein Tourist verblüfft innegehalten hat. Scheint doch der Bug des Scheibenhochhauses wie ein Ozeanriese aus dem abstrakten Wellental des Sockelbaus in den Strassenraum vorzustossen. Man könnte in dieser 1956 vollendeten Perle der italienischen Nachkriegsarchitektur den Geniestreich eines jungen Navigation 17.06.12 13:10Opportunistischer Alleskönner - Neue Zürcher Zeitung Seite 2 von 4http://mobile.nzz.ch/kultur/kunst_architektur/opportunistischer_alleskoenner_1.15553525.html vollendeten Perle der italienischen Nachkriegsarchitektur den Geniestreich eines jungen Wilden vermuten, der den Ballast der Schule abgeworfen und sich auf ein waghalsiges Konstruktionsmanöver eingelassen hat. Doch der damals 49-jährige Moretti wollte sich mit diesem spektakulären Befreiungsschlag von einer ganz anderen Last lösen: seiner monumentalen, mit raffinierter Rhetorik die Macht des Duce verherrlichenden Raumkunst, die vor dem Zweiten Weltkrieg in Bauten, Platzanlagen und Wettbewerbsentwürfen immer neue Triumphe feierte. Monumentale Visionen Am Anfang der umfassenden Werkschau, die derzeit in der Galerie der Architekturakademie Mendrisio zu sehen ist, stehen prachtvolle farbige Präsentationszeichnungen aus den späten 1930er Jahren, als Moretti sich mit Leidenschaft an die Verfeinerung der faschistischen Ikonographie machte. Mit den detailreichen Bildtafeln, die neben der Architektur, dem Raum und dem Licht auch die Ausgestaltung der Aussen- und Innenräume bis hin zu den Mosaiken und Skulpturengruppen wiedergeben, versuchte Moretti die nationalen Wettbewerbe des Palazzo del Littorio und des Piazzale del Impero für sich zu entscheiden. Auf der Empore des Ausstellungssaals sieht man sich mit ihrer martialischen Ausstrahlung konfrontiert. Anschliessend kann man unten im langgestreckten Galerieraum und im separaten Modellsaal die Zeugnisse des vielschichtigen Entwurfsprozesses entschlüsseln. Sie geben einen Eindruck von der Kreativität Morettis, der sich wie viele andere Künstler seiner Zeit – nicht nur in Italien – von den ihm durch die Diktatur gebotenen Möglichkeiten hatte blenden lassen. Doch anders als der geniale Giuseppe Terragni, der an seinem Irrtum zugrunde ging, verstand es der Konformist Moretti, sich nach dem Krieg mit Leichtigkeit neu zu erfinden. Bereits als Student realisierte der im architektonischen Ambiente Roms aufgewachsene Moretti seine ersten Häuser – etwa 1931 eine schöne, vom klassizistischen Mailänder Novecento und vom Vokabular des späteren Staatsarchitekten Marcello Piacentini beeinflusste Stadtvilla in Ostia. Dann entdeckte er die rationalistische Moderne und schuf zwischen 1933 und 1936 mehrere der faschistischen Jugend gewidmete Case Balilla, darunter jene von Trastevere. Während das Zusammenspiel der modernistischen Volumen und des etwas plumpen, mit dem obligaten Balkon versehenen Turms irritiert, vermögen die eleganten Innenräume zu punkten. Solch rationalistischen Fingerübungen folgte die sich durch eine meisterhaft inszenierte Plastizität auszeichnende, später zur Accademia della Scherma umfunktionierte Casa Balilla sperimentale am Foro Mussolini (dem späteren Foro Italico), wo Moretti neben dem Piazzale del Impero auch die geschmäcklerische Palestra del Duce realisierte: einen Marmortempel, in dessen minimalistischen Säulenhallen sich Mussolini ertüchtigen konnte. Damals schon übte sich Moretti in unterschiedlichen Formensprachen und entwarf ganz im Geist der Pittura Metafisica eine rätselhaft anmutende Villa am Meer. Nach dem Krieg kam er für seine faschistische Kollaboration kurz ins Gefängnis. Danach verliess er Rom, um in Mailand den Neuanfang zu wagen. Die ersten Bauten, die mit seiner Firma Cofimprese in der lombardischen Metropole realisierten «Case-Albergo», waren noch dem Rationalismus verpflichtet, veranschaulichten aber mit Lochfenstern oder sich geradezu dekonstruktivistisch von der Tragstruktur ablösenden Fassaden bereits Morettis architektonischen Dialog mit der ungegenständlichen Kunst (etwa eines Lucio Fontana). Zurück in Rom, sagt er sich 1949 mit dem Astrea-Wohnblock, dessen Fassaden schuppenartig abstehen, vom doktrinären Rationalismus los; und mit der mittig gespaltenen Palazzina Girasole (1950), die sich über einem ruppigen Steinsockel erhebt, gelingt ihm sein erster 17.06.12 13:10Opportunistischer Alleskönner - Neue Zürcher Zeitung Seite 3 von 4http://mobile.nzz.ch/kultur/kunst_architektur/opportunistischer_alleskoenner_1.15553525.html ImpressumAGBCopyrightWerbungWechsel zur Webansicht Girasole (1950), die sich über einem ruppigen Steinsockel erhebt, gelingt ihm sein erster Capolavoro der Nachkriegszeit, der zur Inspiration für Robert Venturi, den Papst der Postmoderne, werden sollte. Form und Raum Im selben Jahr gründet er die Zeitschrift «Spazio», in der er die informelle Kunst für die Architektur zu nutzen sucht und neue Anregung bei Borrominis Barock und Michelangelos Manierismus findet. Die von seinem Widersacher, dem eine ethische Architektur fordernden Bruno Zevi, propagierte organische Baukunst stösst auch bei Moretti auf Interesse. Er weiss sie in sein logisch-mathematisches Theoriegebäude zu integrieren, wie ein weiteres Highlight beweist: die auf Kreisen und Ovalen basierende Villa «La Saracena» in Santa Marinella (1957), zu der Annalisa Viati Navone, die zusammen mit Bruno Reichlin die Ausstellung betreute, soeben eine ausführliche Studie veröffentlicht hat. Organische Gestaltungsprinzipien prägen später auch die Watergate-Residenz in Washington (1965), die Thermen von Fiuggi (1969) sowie drei zwischen 1964 und 1972 konzipierte Römer Projekte: den San-Maurizio-Wohnblock, die seltsame, an ein brütendes Huhn erinnernde Chiesa Santa Maria Ecclesiae und die skulpturale Tiefgarage unter dem Park der Villa Borghese. Anders als Zevi verstand Moretti die organische Baukunst nicht als politische Aussage, sondern als rein formale Geste, wie sein im Auftrag des Vatikans projektiertes, aber unrealisiert gebliebenes Sanktuarium am See Genezareth demonstriert. Hier versuchte er Frank Lloyd Wright zu übertreffen. Er mass sich jedoch auch mit anderen Grössen seiner Zeit. So antwortet die zusammen mit dem Meisteringenieur Pier Luigi Nervi geplante Tour de la Bourse in Montreal auf Mies van der Rohes Seagram Building in New York und auf das Pirelli-Hochhaus von Gio Ponti und Nervi in Mailand. Auf all diese Werke geht der opulente Katalog, der leider weder über eine (an sich leicht erstellbare) Liste der realisierten Gebäude noch über ein Werkverzeichnis verfügt, ausführlich ein. Aber selbst die faschistischen Bauten werden in erster Linie in Bezug auf Form und Raum analysiert. Damit wird dem erfindungsreichen Architekten ein verdientes Denkmal errichtet, aber einmal mehr auf eine über Andeutungen hinausgehende kritisch-zeitgeschichtliche Auseinandersetzung mit dem opportunistischen Alleskönner verzichtet. Bis 8. April (Di–Fr von 16–19.30 Uhr, Sa u. So von 13–18 Uhr). Katalog: Luigi Moretti. Razionalismo e trasgressività tra baroc",
  "stand": "2026-07-02T22:42:15"
}