{
  "slug": "Morscher_Architekten",
  "architekt": {
    "name": "Morscher Architekten",
    "nachname": "Morscher",
    "vorname": "Architekten",
    "jahre": [],
    "ordner": "Morscher_Architekten"
  },
  "pfad": "/Volumes/daten/05_Architekten_Synobsis/Morscher_Architekten",
  "projekte": [],
  "projekt_anzahl": 0,
  "inventar": {
    "bilder": 0,
    "dokumente": 0,
    "cad": 0,
    "andere": 0,
    "total": 0
  },
  "dateitypen": {},
  "textauszug": "",
  "embed_doc": "Morscher Architekten",
  "stand": "2026-07-02T22:42:19"
}