{
  "slug": "Poelzig_Hans",
  "architekt": {
    "name": "Poelzig Hans",
    "nachname": "Poelzig Hans",
    "vorname": "",
    "jahre": [],
    "ordner": "Poelzig Hans"
  },
  "pfad": "/Volumes/daten/05_Architekten_Synobsis/Poelzig Hans",
  "projekte": [
    {
      "raw": "Berlin_Charlottenburg_Funkhalle_1924",
      "ort": "Berlin",
      "projekt": "Charlottenburg Funkhalle",
      "jahre": [
        "1924"
      ],
      "titel": "Berlin Charlottenburg Funkhalle 1924"
    },
    {
      "raw": "Berlin_Ideenwettbewerb_Hochhaus",
      "ort": "Berlin",
      "projekt": "Ideenwettbewerb Hochhaus",
      "jahre": [],
      "titel": "Berlin Ideenwettbewerb Hochhaus"
    },
    {
      "raw": "Berlin_Kino_Babylon_Rosa_Luxenburg_Platz_",
      "ort": "Berlin",
      "projekt": "Kino Babylon Rosa Luxenburg Platz ",
      "jahre": [],
      "titel": "Berlin Kino Babylon Rosa Luxenburg Platz"
    },
    {
      "raw": "Berlin_Platz_der_Republik_Ueberbauungsplan_Entwurf",
      "ort": "Berlin",
      "projekt": "Platz der Republik Ueberbauungsplan Entwurf",
      "jahre": [],
      "titel": "Berlin Platz der Republik Ueberbauungsplan Entwurf"
    },
    {
      "raw": "Berlin_Schauspielhaus",
      "ort": "Berlin",
      "projekt": "Schauspielhaus",
      "jahre": [],
      "titel": "Berlin Schauspielhaus"
    },
    {
      "raw": "Chemnitz_Textilfabrik_Sigmund_Goeritz_A_G_1926",
      "ort": "Chemnitz",
      "projekt": "Textilfabrik Sigmund Goeritz A G",
      "jahre": [
        "1926"
      ],
      "titel": "Chemnitz Textilfabrik Sigmund Goeritz A G 1926"
    },
    {
      "raw": "Dresden_Bank_1921",
      "ort": "Dresden",
      "projekt": "Bank",
      "jahre": [
        "1921"
      ],
      "titel": "Dresden Bank 1921"
    },
    {
      "raw": "Entwurf_Tankstelle_Reichskraftsprit",
      "ort": "Entwurf",
      "projekt": "Tankstelle Reichskraftsprit",
      "jahre": [],
      "titel": "Entwurf Tankstelle Reichskraftsprit"
    },
    {
      "raw": "Hamburg_Wasserturm",
      "ort": "Hamburg",
      "projekt": "Wasserturm",
      "jahre": [],
      "titel": "Hamburg Wasserturm"
    },
    {
      "raw": "Hannover_Haus_des_Rundfunks",
      "ort": "Hannover",
      "projekt": "Haus des Rundfunks",
      "jahre": [],
      "titel": "Hannover Haus des Rundfunks"
    },
    {
      "raw": "Luban_Schwefelsaeurefabrik",
      "ort": "Luban",
      "projekt": "Schwefelsaeurefabrik",
      "jahre": [],
      "titel": "Luban Schwefelsaeurefabrik"
    },
    {
      "raw": "Moskau_Palast_der_Sowjets",
      "ort": "Moskau",
      "projekt": "Palast der Sowjets",
      "jahre": [],
      "titel": "Moskau Palast der Sowjets"
    },
    {
      "raw": "Posen_Wasserturm",
      "ort": "Posen",
      "projekt": "Wasserturm",
      "jahre": [],
      "titel": "Posen Wasserturm"
    },
    {
      "raw": "Preslau_Buero_Geschaeftshaus",
      "ort": "Preslau",
      "projekt": "Buero Geschaeftshaus",
      "jahre": [],
      "titel": "Preslau Buero Geschaeftshaus"
    },
    {
      "raw": "Thuering",
      "ort": "Thuering",
      "projekt": "Thuering",
      "jahre": [],
      "titel": "Thuering"
    }
  ],
  "projekt_anzahl": 15,
  "inventar": {
    "bilder": 38,
    "dokumente": 8,
    "cad": 0,
    "andere": 3,
    "total": 49
  },
  "dateitypen": {
    ".jpg": 33,
    ".pdf": 7,
    ".tif": 5,
    ".pages": 1,
    ".pptx": 1,
    ".docx": 1,
    ".psd": 1
  },
  "textauszug": "Zwischen Tradition und ModerneDas Grosse Schauspielhaus BerlinMax Reinhardt und Hans Pölzig1919 7. November 2013 –Drama und Architektur –Janina Zollinger & Romana Martic Innenraum Grosses Schauspielhaus BerlinZeichnung: Hans Pölzig 1919 Zwischen Tradition und Moderne –Das Grosse Schauspielhaus Berlin –Max Reinhardt und Hans Pölzig 7. November 2013 –Drama und Architektur –Janina Zollinger & Romana Martic „Es handelt sich um eine Art Folgerichtigkeit und poetische Gerechtigkeit, dass die beiden merkwürdigen und begabten Männer endlich zusammengetroffen sind. Sie mussten sich finden.lKarl Scheffler, 1920 Zwischen Tradition und Moderne –Das Grosse Schauspielhaus Berlin –Max Reinhardt und Hans Pölzig 7. November 2013 –Drama und Architektur –Janina Zollinger & Romana Martic Max Reinhardt –1873 -1943 Hans Pölzig –1869-1936 Die Wiederbelebung des antiken Theaters und der Zirkus:Amphitheater und ManegeGrundriss–Hans Pölzig, Grosses Schauspielhaus 1919 Zwischen Tradition und Moderne –Das Grosse Schauspielhaus Berlin –Max Reinhardt und Hans Pölzig 7. November 2013 –Drama und Architektur –Janina Zollinger & Romana Martic Die Roaring Twenties in Berlin: Nachkriegstaumel und Sucht nach SpektakelDie Ausstattungsrevue im Berlin der 20er Jahre Zwischen Tradition und Moderne –Das Grosse Schauspielhaus Berlin –Max Reinhardt und Hans Pölzig 7. November 2013 –Drama und Architektur –Janina Zollinger & Romana Martic Die Roaring Twenties in Berlin: Nachkriegstaumel und Sucht nach Spektakel„Weltbühne Berlinl, 3sat Zwischen Tradition und Moderne –Das Grosse Schauspielhaus Berlin –Max Reinhardt und Hans Pölzig 7. November 2013 –Drama und Architektur –Janina Zollinger & Romana Martic CHRIST -GANTENBEIN.ARCH.ETHZ.CH EMANUEL CHRIST & CHRISTOPH GANTENBEIN FS 193.4.19 POELZIG- ARTIG EXPRESSIVE KONSTRUKTION 7 PRINZIPIEN 1. KUNSTFORM = BAUFORM Festspielhaus, Salzburg, 1920-22 CHRIST -GANTENBEIN.ARCH.ETHZ.CH EMANUEL CHRIST & CHRISTOPH GANTENBEIN FS 193.4.19 POELZIG- ARTIG EXPRESSIVE KONSTRUKTION 7 PRINZIPIEN 1. KUNSTFORM = BAUFORM Festspielhaus, Salzburg, 1920-22 Poelzigartig Expressive Konstruktion 7. Prinzipien 1. Kunstform = Bauform 2. Die Sehnsucht nach der massiven Wand 3. Grossform und Curtain Wall 4. Der Plastisch Geformte Körper digital gebaut 5. Die Animation der Oberfläche 6. Vom Raum her gedacht 7. Verkleidungsarchitektur Hans Poelzig Bankgebäude Dresden 1921 37 References 39 References Bibliography Internet http://architekturmuseum.ub.tu-berlin.de/index.php?set=1&p=61&D1=Poelzig&D2=Ha ns&D3=Bankgeb%E4ude%2C+Dresden http://www.das-neue-dresden.de/stadthaus-dresden1923.html Section, 1:500 Plan Elevation 38 FS 2012 The Tall Office Building Artitistically Considered 4.1 4.16 4.6 4.5 4.4 4.3 4.2 4.1 2.5 1.72 0.91.771.821.891.921.971.9 1.45 4.25 60.60 VIEW 1 : 50 35.5m 6.6m 0.8m 22.5m 0.8m 4.6m 4.5m 4.3m 4.3m 4.0m 3.5m 4.6m 3.2m SECTION 1 : 50",
  "embed_doc": "Poelzig Hans | Berlin Charlottenburg Funkhalle 1924 | Berlin Ideenwettbewerb Hochhaus | Berlin Kino Babylon Rosa Luxenburg Platz | Berlin Platz der Republik Ueberbauungsplan Entwurf | Berlin Schauspielhaus | Chemnitz Textilfabrik Sigmund Goeritz A G 1926 | Dresden Bank 1921 | Entwurf Tankstelle Reichskraftsprit | Hamburg Wasserturm | Hannover Haus des Rundfunks | Luban Schwefelsaeurefabrik | Moskau Palast der Sowjets | Posen Wasserturm | Preslau Buero Geschaeftshaus | Thuering Thuering | Zwischen Tradition und ModerneDas Grosse Schauspielhaus BerlinMax Reinhardt und Hans Pölzig1919 7. November 2013 –Drama und Architektur –Janina Zollinger & Romana Martic Innenraum Grosses Schauspielhaus BerlinZeichnung: Hans Pölzig 1919 Zwischen Tradition und Moderne –Das Grosse Schauspielhaus Berlin –Max Reinhardt und Hans Pölzig 7. November 2013 –Drama und Architektur –Janina Zollinger & Romana Martic „Es handelt sich um eine Art Folgerichtigkeit und poetische Gerechtigkeit, dass die beiden merkwürdigen und begabten Männer endlich zusammengetroffen sind. Sie mussten sich finden.lKarl Scheffler, 1920 Zwischen Tradition und Moderne –Das Grosse Schauspielhaus Berlin –Max Reinhardt und Hans Pölzig 7. November 2013 –Drama und Architektur –Janina Zollinger & Romana Martic Max Reinhardt –1873 -1943 Hans Pölzig –1869-1936 Die Wiederbelebung des antiken Theaters und der Zirkus:Amphitheater und ManegeGrundriss–Hans Pölzig, Grosses Schauspielhaus 1919 Zwischen Tradition und Moderne –Das Grosse Schauspielhaus Berlin –Max Reinhardt und Hans Pölzig 7. November 2013 –Drama und Architektur –Janina Zollinger & Romana Martic Die Roaring Twenties in Berlin: Nachkriegstaumel und Sucht nach SpektakelDie Ausstattungsrevue im Berlin der 20er Jahre Zwischen Tradition und Moderne –Das Grosse Schauspielhaus Berlin –Max Reinhardt und Hans Pölzig 7. November 2013 –Drama und Architektur –Janina Zollinger & Romana Martic Die Roaring Twenties in Berlin: Nachkriegstaumel und Sucht nach Spektakel„Weltbühne Berlinl, 3sat Zwischen Tradition und Moderne –Das Grosse Schauspielhaus Berlin –Max Reinhardt und Hans Pölzig 7. November 2013 –Drama und Architektur –Janina Zollinger & Romana Martic CHRIST -GANTENBEIN.ARCH.ETHZ.CH EMANUEL CHRIST & CHRISTOPH GANTENBEIN FS 193.4.19 POELZIG- ARTIG EXPRESSIVE KONSTRUKTION 7 PRINZIPIEN 1. KUNSTFORM = BAUFORM Festspielhaus, Salzburg, 1920-22 CHRIST -GANTENBEIN.ARCH.ETHZ.CH EMANUEL CHRIST & CHRISTOPH GANTENBEIN FS 193.4.19 POELZIG- ARTIG EXPRESSIVE KONSTRUKTION 7 PRINZIPIEN 1. KUNSTFORM = BAUFORM Festspielhaus, Salzburg, 1920-22 Poelzigartig Expressive Konstruktion 7. Prinzipien 1. Kunstform = Bauform 2. Die Sehnsucht nach der massiven Wand 3. Grossform und Curtain Wall 4. Der Plastisch Geformte Körper digital gebaut 5. Die Animation der Oberfläche 6. Vom Raum her gedacht 7. Verkleidungsarchitektur Hans Poelzig Bankgebäude Dresden 1921 37 References 39 References Bibliography Internet http://architekturmuseum.ub.tu-berlin.de/index.php?set=1&p=61&D1=Poelzig&D2=Ha ns&D3=Bankgeb%E4ude%2C+Dresden http://www.das-neue-dresden.de/stadthaus-dresden1923.html Section, 1:500 Plan Elevation 38 FS 2012 The Tall Office Building Artitistically Considered 4.1 4.16 4.6 4.5 4.4 4.3 4.2 4.1 2.5 1.72 0.91.771.821.891.921.971.9 1.45 4.25 60.60 VIEW 1 : 50 35.5m 6.6m 0.8m 22.5m 0.8m 4.6m 4.5m 4.3m 4.3m 4.0m 3.5m 4.6m 3.2m SECTION 1 : 50",
  "stand": "2026-07-02T22:44:53"
}